; Test.j

; Generated by ClassFileAnalyzer (Can)
; Analyzer and Disassembler for Java class files
; (Jasmin syntax 2, http://jasmin.sourceforge.net)
;
; ClassFileAnalyzer, version 0.7.0 


.bytecode 61.0
.source Test.java
.class public Test
.super java/lang/Object

.method public <init>()V
  .limit stack 1
  .limit locals 1
  .line 2
  0: aload_0
  1: invokespecial java/lang/Object/<init>()V
  4: return
.end method

.method public static foo([Z)V
  .limit stack 3
  .limit locals 1
  .line 5
  0: aload_0
  1: iconst_0
  2: iconst_1
  3: bastore
  .line 6
  4: return
.end method

.method public static main([Ljava/lang/String;)V
  .limit stack 4
  .limit locals 2
  .line 9
  0: iconst_2
  1: newarray boolean
  3: dup
  4: iconst_0
  5: iconst_0
  6: bastore
  7: dup
  8: iconst_1
  9: iconst_0
  10: bastore
  11: astore_1
  .line 10
  12: aload_1
  13: invokestatic Test/foo([Z)V
  .line 11
  16: aload_1
  17: iconst_0
  18: baload
  19: invokestatic io/writeBool(Z)V
  .line 12
  22: aload_1
  23: iconst_1
  24: baload
  25: invokestatic io/writeBool(Z)V
  .line 13
  28: return
.end method

